{
  "SWG": {
    "LoginAddress": "swg.example.com",
    "SWGServerName": "Dantooine",
    "LoginPort": 44453,
    "Username": "r2d2",
    "Password": "beepboop",
    "Character": "C-3PO",
    "ChatRoom": "SWG.Dantooine.Cantina",
    "verboseSWGLogging": false,
    "inOrderDelivery": false,
    "inOrderStallSecs": 10,
    "fragmentSeqFix": false
  },
  "Discord": {
    "BotName": "C-3PO Protocol Droid",
    "PresenceName": "translating",
    "BotToken": "YOUR_DISCORD_BOT_TOKEN_HERE",
    "ServerID": "123456789012345678",
    "ChatChannel": "cantina-chat",
    "NotificationChannel": "server-status",
    "NotificationMentionRole": "Server Admin",
    "NotificationMentionUserID": "111111111111111111",
    "AdminUsers": {
      "111111111111111111": "Luke Skywalker",
      "222222222222222222": "Han Solo",
      "333333333333333333": "Leia Organa"
    },
    "AdminChannels": {
      "444444444444444444": "#rebel-command",
      "555555555555555555": "#droid-workshop"
    },
    "AutoRestartTimer": 0,
    "verboseDiscordLogging": false
  }
}
